osintcat/__init__.py
osintcat/core.py
osintcat-0.3.dist-info/METADATA
osintcat-0.3.dist-info/WHEEL
osintcat-0.3.dist-info/top_level.txt
osintcat-0.3.dist-info/RECORD
