Metadata-Version: 2.4
Name: osintcat
Version: 0.3
Summary: python package for osintcat.ru
Home-page: https://github.com/stormylol/osintcat
Author: flux
Classifier: Programming Language :: Python :: 3
Requires-Python: >=3.6
Requires-Dist: requests
Dynamic: author
Dynamic: classifier
Dynamic: description-content-type
Dynamic: home-page
Dynamic: requires-dist
Dynamic: requires-python
Dynamic: summary
